Metadata-Version: 2.1
Name: pystiche
Version: 1.0.1
Summary: Framework for Neural Style Transfer built upon PyTorch
Home-page: https://github.com/pmeier/pystiche
Author: Philip Meier
Author-email: github.pmeier@posteo.de
License: BSD-3-Clause
Project-URL: Bug Tracker, https://github.com/pystiche/pystiche/issues
Project-URL: Documentation, https://pystiche.readthedocs.io
Project-URL: Source Code, https://github.com/pystiche/pystiche
Keywords: neural-style-transfer,framework,pytorch
Platform: any
Classifier: Development Status :: 5 - Production/Stable
Classifier: Intended Audience :: Developers
Classifier: Intended Audience :: Education
Classifier: Intended Audience :: Science/Research
Classifier: License :: OSI Approved :: BSD License
Classifier: Programming Language :: Python :: 3.6
Classifier: Programming Language :: Python :: 3.7
Classifier: Programming Language :: Python :: 3.8
Classifier: Programming Language :: Python :: 3.9
Classifier: Topic :: Scientific/Engineering
Classifier: Topic :: Scientific/Engineering :: Artificial Intelligence
Classifier: Topic :: Software Development :: Libraries :: Application Frameworks
Classifier: Topic :: Software Development :: Libraries :: Python Modules
Classifier: Typing :: Typed
Requires-Python: >=3.6
License-File: LICENSE
Requires-Dist: torch (>=1.7)
Requires-Dist: torchvision (>=0.8)
Requires-Dist: pillow (!=8.3.0)
Requires-Dist: tqdm
